{
  "lemma_to_index": {
    "kṛ": 0,
    "bhū": 1,
    "vid": 2,
    "hu": 3,
    "as": 4,
    "yaj": 5,
    "ah": 6,
    "vac": 7,
    "dhā": 8,
    "i": 9,
    "jan": 10,
    "gam": 11,
    "brū": 12,
    "dā": 13,
    "grah": 14,
    "sthā": 15,
    "pā": 16,
    "sṛj": 17,
    "ālabh": 18,
    "car": 19,
    "ādhā": 20,
    "pū": 21,
    "ādā": 22,
    "han": 23,
    "nidhā": 24,
    "bhṛ": 25,
    "paś": 26,
    "yuj": 27,
    "śru": 28,
    "pratiṣṭhā": 29,
    "vad": 30,
    "upās": 31,
    "ji": 32,
    "āp": 33,
    "aś": 34,
    "hvā": 35,
    "gā": 36,
    "e": 37,
    "vṛ": 38,
    "yā": 39,
    "dṛś": 40,
    "añj": 41,
    "su": 42,
    "man": 43,
    "juṣ": 44,
    "iṣ": 45,
    "hṛ": 46,
    "av": 47,
    "nī": 48,
    "kāmay": 49,
    "ās": 50,
    "pṛ": 51,
    "āgam": 52,
    "vah": 53,
    "stu": 54,
    "jap": 55,
    "tap": 56,
    "duh": 57,
    "upasthā": 58,
    "yam": 59,
    "udi": 60,
    "muc": 61,
    "upe": 62,
    "āhṛ": 63,
    "praviś": 64,
    "nirvap": 65,
    "jīv": 66,
    "prayam": 67,
    "avarudh": 68,
    "vas": 69,
    "anvah": 70,
    "anubrū": 71,
    "upahvā": 72,
    "prāś": 73,
    "vṛdh": 74,
    "prī": 75,
    "hiṃs": 76,
    "sambhū": 77,
    "dviṣ": 78,
    "prajan": 79,
    "sambhṛ": 80,
    "prokṣ": 81,
    "samṛdh": 82,
    "apahan": 83,
    "ad": 84,
    "pracch": 85,
    "tṛ": 86,
    "math": 87,
    "sad": 88,
    "janay": 89,
    "bandh": 90,
    "praṇī": 91,
    "pre": 92,
    "jñā": 93,
    "upaviś": 94,
    "dhāray": 95,
    "utkram": 96,
    "dīkṣ": 97,
    "vijñā": 98,
    "hā": 99,
    "paridhā": 100,
    "ācakṣ": 101,
    "adhī": 102,
    "vaś": 103,
    "pratigrah": 104,
    "īś": 105,
    "tan": 106,
    "vī": 107,
    "utthā": 108,
    "samardhay": 109,
    "prahṛ": 110,
    "bhuj": 111,
    "śaṃs": 112,
    "bhī": 113,
    "khan": 114,
    "anumantray": 115,
    "rakṣ": 116,
    "abhimantray": 117,
    "sic": 118,
    "prayuj": 119,
    "anuvac": 120,
    "pratiṣṭhāpay": 121,
    "āruh": 122,
    "chid": 123,
    "dṛh": 124,
    "prapad": 125,
    "parigrah": 126,
    "ci": 127,
    "gṛ": 128,
    "naś": 129,
    "śrapay": 130,
    "prasū": 131,
    "sah": 132,
    "upaspṛś": 133,
    "snā": 134,
    "bhid": 135,
    "āgā": 136,
    "sampad": 137,
    "kṣi": 138,
    "prajñā": 139,
    "āśās": 140,
    "śak": 141,
    "anuvical": 142,
    "indh": 143,
    "mad": 144,
    "śudh": 145,
    "ānī": 146,
    "sac": 147,
    "pratipad": 148,
    "samindh": 149,
    "vṛt": 150,
    "ṛch": 151,
    "upadhāv": 152,
    "cit": 153,
    "hi": 154,
    "mṛ": 155,
    "kāray": 156,
    "śam": 157,
    "ācam": 158,
    "āvap": 159,
    "ucchri": 160,
    "vyadh": 161,
    "ninī": 162,
    "udgā": 163,
    "saṃpreṣ": 164,
    "kalpay": 165,
    "dhṛ": 166,
    "śī": 167,
    "sāday": 168,
    "uddhṛ": 169,
    "abhimṛś": 170,
    "vardhay": 171,
    "īḍ": 172,
    "ārabh": 173,
    "prāp": 174,
    "gopāy": 175,
    "saṃsṛj": 176,
    "ruh": 177,
    "tṛp": 178,
    "abhighāray": 179,
    "āviś": 180,
    "prajanay": 181,
    "dhyā": 182,
    "ṛdh": 183,
    "jinv": 184,
    "ruc": 185,
    "upadhā": 186,
    "prakṣālay": 187,
    "pac": 188,
    "stṛ": 189,
    "śri": 190,
    "vyākhyā": 191,
    "sammṛj": 192,
    "tarpay": 193,
    "unnī": 194,
    "ī": 195,
    "avado": 196,
    "saṃdhā": 197,
    "vap": 198,
    "adhiśri": 199,
    "vācay": 200,
    "kﾱp": 201,
    "viś": 202,
    "dāś": 203,
    "pat": 204,
    "bhakṣay": 205,
    "avadhā": 206,
    "dah": 207,
    "vraśc": 208,
    "gamay": 209,
    "parī": 210,
    "anvārabh": 211,
    "saṃsthā": 212,
    "ram": 213,
    "utsṛj": 214,
    "abhihu": 215,
    "antardhā": 216,
    "upākṛ": 217,
    "upavas": 218,
    "pradā": 219,
    "vṛj": 220,
    "śrī": 221,
    "riṣ": 222,
    "trā": 223,
    "atī": 224,
    "saṃskṛ": 225,
    "pravac": 226,
    "nam": 227,
    "mā": 228,
    "prāṇ": 229,
    "nud": 230,
    "utthāpay": 231,
    "abhyukṣ": 232,
    "yājay": 233,
    "pad": 234,
    "krand": 235,
    "labh": 236,
    "apakram": 237,
    "alaṃkṛ": 238,
    "upajīv": 239,
    "śram": 240,
    "paridā": 241,
    "apī": 242,
    "īkṣ": 243,
    "sṛ": 244,
    "kṣar": 245,
    "pinv": 246,
    "jṛ": 247,
    "upasamādhā": 248,
    "abhyādhā": 249,
    "svap": 250,
    "upastṛ": 251,
    "nivap": 252,
    "atiric": 253,
    "sidh": 254,
    "kram": 255,
    "yāc": 256,
    "abhivad": 257,
    "udyam": 258,
    "pāyay": 259,
    "udvāsay": 260,
    "pratimuc": 261,
    "avekṣ": 262,
    "atikram": 263,
    "anvi": 264,
    "dhāv": 265,
    "pyā": 266,
    "āvṛt": 267,
    "upasṛ": 268,
    "takṣ": 269,
    "saṃmā": 270,
    "anuman": 271,
    "prath": 272,
    "āpyā": 273,
    "preṣ": 274,
    "parilikh": 275,
    "parivye": 276,
    "paristṛ": 277,
    "āmantray": 278,
    "saṃjñapay": 279,
    "śamay": 280,
    "rādh": 281,
    "niyuj": 282,
    "pramuc": 283,
    "mi": 284,
    "anugam": 285,
    "ācchṛd": 286,
    "upaveśay": 287,
    "dīdī": 288,
    "rā": 289,
    "śās": 290,
    "pare": 291,
    "nikhan": 292,
    "svad": 293,
    "parihṛ": 294,
    "abhitap": 295,
    "praśaṃs": 296,
    "arc": 297,
    "abhipad": 298,
    "mṛj": 299,
    "āsad": 300,
    "abhicar": 301,
    "rocay": 302,
    "upasāday": 303,
    "niras": 304,
    "apidhā": 305,
    "bādh": 306,
    "jval": 307,
    "ābhṛ": 308,
    "bhrāj": 309,
    "mī": 310,
    "abhyañj": 311,
    "pūray": 312,
    "yu": 313,
    "māday": 314,
    "bhaj": 315,
    "devay": 316,
    "bhā": 317,
    "ṛṣ": 318,
    "van": 319,
    "vājay": 320,
    "śubh": 321,
    "āvah": 322,
    "visṛj": 323,
    "upasad": 324,
    "prabrū": 325,
    "āśrāvay": 326,
    "utpū": 327,
    "pravas": 328,
    "bhojay": 329,
    "saṃcar": 330,
    "śuc": 331,
    "budh": 332,
    "yat": 333,
    "āpyāyay": 334,
    "abhiṣic": 335,
    "sammṛś": 336,
    "vimuc": 337,
    "paryūh": 338,
    "parāpat": 339,
    "upadiś": 340,
    "avasic": 341,
    "varjay": 342,
    "anuvid": 343,
    "saṃvid": 344,
    "puṣ": 345,
    "cakṣ": 346,
    "vidh": 347,
    "nū": 348,
    "guh": 349,
    "san": 350,
    "dīv": 351,
    "nah": 352,
    "ādṛ": 353,
    "āsāday": 354,
    "krī": 355,
    "anuprahṛ": 356,
    "spṛdh": 357,
    "sṛp": 358,
    "dhū": 359,
    "vivakṣ": 360,
    "pracchid": 361,
    "visraṃs": 362,
    "gras": 363,
    "skand": 364,
    "pṛṇ": 365,
    "syand": 366,
    "vitan": 367,
    "vṛṣ": 368,
    "vadh": 369,
    "pariśri": 370,
    "atimuc": 371,
    "bhāṣ": 372,
    "upanam": 373,
    "āpad": 374,
    "upagā": 375,
    "vidhā": 376,
    "āstṛ": 377,
    "adhiruh": 378,
    "upahan": 379,
    "sru": 380,
    "adhivah": 381,
    "vibhā": 382,
    "yudh": 383,
    "sū": 384,
    "nāśay": 385,
    "upayam": 386,
    "spṛś": 387,
    "niṣad": 388,
    "nirmath": 389,
    "saṃyuj": 390,
    "coday": 391,
    "dhṛṣ": 392,
    "ādiś": 393,
    "samañj": 394,
    "nivṛt": 395,
    "anvāyat": 396,
    "pramad": 397,
    "mahīy": 398,
    "jāgṛ": 399,
    "mṛḍ": 400,
    "ape": 401,
    "gup": 402,
    "vyṛdh": 403,
    "saṃśā": 404,
    "pratyah": 405,
    "anudru": 406,
    "paryagnikṛ": 407,
    "vyath": 408,
    "pratiṣic": 409,
    "ākram": 410,
    "parikram": 411,
    "samāp": 412,
    "anujñā": 413,
    "prapāday": 414,
    "āsthā": 415,
    "dīp": 416,
    "vikṛ": 417,
    "saṃvad": 418,
    "saṃnī": 419,
    "prāśay": 420,
    "bhikṣ": 421,
    "īray": 422,
    "īr": 423,
    "śikṣ": 424,
    "stanay": 425,
    "upāp": 426,
    "antari": 427,
    "prāh": 428,
    "arpay": 429,
    "prastu": 430,
    "prekṣ": 431,
    "rud": 432,
    "vartay": 433,
    "vyāvṛt": 434,
    "viriṣ": 435,
    "dhūpay": 436,
    "anuṣṭhā": 437,
    "atisṛj": 438,
    "nimṛj": 439,
    "upalip": 440,
    "niṣkram": 441,
    "pratitap": 442,
    "vihṛ": 443,
    "avokṣ": 444,
    "anuśās": 445,
    "apān": 446,
    "pramī": 447,
    "pṛc": 448,
    "pariśiṣ": 449,
    "vyāhṛ": 450,
    "mārjay": 451,
    "ude": 452,
    "pravṛ": 453,
    "arh": 454,
    "abhiji": 455,
    "ācar": 456,
    "paryukṣ": 457,
    "ukṣ": 458,
    "pratī": 459,
    "saṃnah": 460,
    "pracchāday": 461,
    "samutthā": 462,
    "lip": 463,
    "anusṛj": 464,
    "saṃtan": 465,
    "ric": 466,
    "dham": 467,
    "kṛṣ": 468,
    "vand": 469,
    "dru": 470,
    "krīḍ": 471,
    "kanikrad": 472,
    "vikram": 473,
    "āyam": 474,
    "piṣ": 475,
    "vibhaj": 476,
    "ājan": 477,
    "avaruh": 478,
    "vyūh": 479,
    "saṃkﾱp": 480,
    "vaṣaṭkṛ": 481,
    "unmṛj": 482,
    "avāp": 483,
    "pratidhā": 484,
    "upāvṛt": 485,
    "stambh": 486,
    "upasṛj": 487,
    "vipat": 488,
    "śā": 489,
    "chṛd": 490,
    "āśay": 491,
    "ullikh": 492,
    "vāś": 493,
    "pariṣic": 494,
    "uddhan": 495,
    "saṃviś": 496,
    "pṛtany": 497,
    "pravṛj": 498,
    "arātīy": 499,
    "jū": 500,
    "sā": 501,
    "āhu": 502,
    "ghas": 503,
    "pariṣvaj": 504,
    "pravah": 505,
    "dhūrv": 506,
    "grāhay": 507,
    "vyācakṣ": 508,
    "pratan": 509,
    "prās": 510,
    "kṛt": 511,
    "avasṛj": 512,
    "abhiśaṃs": 513,
    "avaguh": 514,
    "parimā": 515,
    "praṇud": 516,
    "abhipīḍay": 517,
    "und": 518,
    "parisamūh": 519,
    "saṃhan": 520,
    "ucchiṣ": 521,
    "vivas": 522,
    "abhyudi": 523,
    "āvṛ": 524,
    "bodhay": 525,
    "ej": 526,
    "pariṣkṛ": 527,
    "dhī": 528,
    "randhay": 529,
    "parāji": 530,
    "prasthā": 531,
    "samavado": 532,
    "saṃsthāpay": 533,
    "upasaṃgrah": 534,
    "āsic": 535,
    "tyaj": 536,
    "pracar": 537,
    "adhiṣṭhā": 538,
    "prathay": 539,
    "adhigam": 540,
    "tṛṣ": 541,
    "ri": 542,
    "vye": 543,
    "abhidhā": 544,
    "niṣkrī": 545,
    "kīrtay": 546,
    "sami": 547,
    "udvap": 548,
    "śṛ": 549,
    "parāmṛś": 550,
    "ābandh": 551,
    "vicchid": 552,
    "pariṇī": 553,
    "avasthāpay": 554,
    "mud": 555,
    "muh": 556,
    "anviṣ": 557,
    "bhiṣajy": 558,
    "udgrah": 559,
    "vigā": 560,
    "rih": 561,
    "uruṣy": 562,
    "ruj": 563,
    "khyā": 564,
    "mṛḍay": 565,
    "nakṣ": 566,
    "āvāhay": 567,
    "śraddhā": 568,
    "acchāi": 569,
    "ācchid": 570,
    "nirmā": 571,
    "udūh": 572,
    "pradah": 573,
    "upanidhā": 574,
    "āvartay": 575,
    "rāj": 576,
    "mah": 577,
    "rabh": 578,
    "rudh": 579,
    "sampṛc": 580,
    "duṣ": 581,
    "abhivāday": 582,
    "viṣṭhā": 583,
    "āyā": 584,
    "ātan": 585,
    "cyu": 586,
    "anūpasthā": 587,
    "jighṛkṣay": 588,
    "saṃspṛś": 589,
    "vraj": 590,
    "pravṛt": 591,
    "abhyāvṛt": 592,
    "prahi": 593,
    "samīkṣ": 594,
    "ve": 595,
    "avastṛ": 596,
    "dhi": 597,
    "vibhū": 598,
    "johav": 599,
    "vā": 600,
    "siṣās": 601,
    "niyam": 602,
    "spṛ": 603,
    "krudh": 604,
    "saṃgam": 605,
    "svaday": 606,
    "saṃtap": 607,
    "āhvā": 608,
    "atihṛ": 609,
    "prayā": 610,
    "nirūh": 611,
    "avaśiṣ": 612,
    "abhyave": 613,
    "āplāvay": 614,
    "pratīkṣ": 615,
    "upanī": 616,
    "abhīndh": 617,
    "upavad": 618,
    "avanī": 619,
    "āpṛṇ": 620,
    "niṣṭap": 621,
    "īps": 622,
    "pratyuṣ": 623,
    "saṃnam": 624,
    "samaś": 625,
    "pravad": 626,
    "paryāvṛt": 627,
    "pratyāśrāvay": 628,
    "vyardhay": 629,
    "upotthā": 630,
    "avasthā": 631,
    "prasṛ": 632,
    "āghāray": 633,
    "pratinand": 634,
    "ācchāday": 635,
    "abhiṣṭhā": 636,
    "pratyūh": 637,
    "upamantray": 638,
    "iṣay": 639,
    "rad": 640,
    "vakṣ": 641,
    "ru": 642,
    "abhivac": 643,
    "pravṛh": 644,
    "abhyāyam": 645,
    "utkhid": 646,
    "likh": 647,
    "vinī": 648,
    "arhay": 649,
    "samādhā": 650,
    "abhyupe": 651,
    "udāhṛ": 652,
    "smṛ": 653,
    "same": 654,
    "ran": 655,
    "cyāvay": 656,
    "dips": 657,
    "vyatiṣañj": 658,
    "vāsay": 659,
    "pratyabhighāray": 660,
    "pūjay": 661,
    "saṃnidhā": 662,
    "paridhāpay": 663,
    "radh": 664,
    "upagrah": 665,
    "anubhū": 666,
    "viji": 667,
    "saṃsparśay": 668,
    "nirbhid": 669,
    "abhidru": 670,
    "ativah": 671,
    "dyut": 672,
    "ābhū": 673,
    "upacar": 674,
    "praṇed": 675,
    "viṣā": 676,
    "paricar": 677,
    "parimṛj": 678,
    "saṃgrah": 679,
    "parivṛ": 680,
    "upahu": 681,
    "saṃśās": 682,
    "snāpay": 683,
    "sambhāṣ": 684,
    "hiṃkṛ": 685,
    "pratihṛ": 686,
    "upagam": 687,
    "niṣṭhā": 688,
    "dih": 689,
    "ceṣṭ": 690,
    "marmṛj": 691,
    "pratibudh": 692,
    "jyā": 693,
    "āve": 694,
    "pātay": 695,
    "abhī": 696,
    "hary": 697,
    "aj": 698,
    "hvṛ": 699,
    "nihan": 700,
    "saṃyat": 701,
    "upakalpay": 702,
    "anvādhā": 703,
    "abhijan": 704,
    "lū": 705,
    "abhiṣṭu": 706,
    "pralip": 707,
    "pariviṣ": 708,
    "vāpay": 709,
    "anugā": 710,
    "śiṣ": 711,
    "anupraviś": 712,
    "rej": 713,
    "mand": 714,
    "prāv": 715,
    "pravid": 716,
    "sthāpay": 717,
    "roro": 718,
    "sapary": 719,
    "kan": 720,
    "āvraśc": 721,
    "ārpay": 722,
    "parivṛj": 723,
    "āvad": 724,
    "prasic": 725,
    "darśay": 726,
    "pīḍay": 727,
    "nigrah": 728,
    "samprayam": 729,
    "prahu": 730,
    "upahṛ": 731,
    "saṃstṛ": 732,
    "prabhū": 733,
    "pāray": 734,
    "jighāṃs": 735,
    "sādh": 736,
    "vṛh": 737,
    "dabh": 738,
    "utprayam": 739,
    "ujji": 740,
    "śap": 741,
    "prakram": 742,
    "pratimantray": 743,
    "prabandh": 744,
    "upālabh": 745,
    "vijijiñās": 746,
    "āplu": 747,
    "saṃjñā": 748,
    "jigīṣ": 749,
    "tam": 750,
    "avadhū": 751,
    "nirmṛj": 752,
    "nand": 753,
    "avasā": 754,
    "uddru": 755,
    "vyākṛ": 756,
    "samānī": 757,
    "pratyākram": 758,
    "prayu": 759,
    "parivāsay": 760,
    "pradru": 761,
    "abhisampad": 762,
    "abhigā": 763,
    "nigad": 764,
    "samupāśri": 765,
    "abhidās": 766,
    "vivās": 767,
    "gāh": 768,
    "patay": 769,
    "upamṛj": 770,
    "upayuj": 771,
    "prādurbhū": 772,
    "anuprajan": 773,
    "pragā": 774,
    "praveṣṭay": 775,
    "virāj": 776,
    "prāpay": 777,
    "abhijñā": 778,
    "vidhvaṃs": 779,
    "samāvṛt": 780,
    "sammi": 781,
    "abhisaṃviś": 782,
    "mahay": 783,
    "anupaś": 784,
    "nilip": 785,
    "yavay": 786,
    "prā": 787,
    "nirudh": 788,
    "ṛj": 789,
    "smi": 790,
    "dhanv": 791,
    "svar": 792,
    "mṛṇ": 793,
    "aparudh": 794,
    "avakṛ": 795,
    "anugup": 796,
    "mīmāṃs": 797,
    "edh": 798,
    "samave": 799,
    "avapad": 800,
    "abhipravraj": 801,
    "pravraj": 802,
    "saṃvṛt": 803,
    "abhiman": 804,
    "abhikṣar": 805,
    "abhiprāṇ": 806,
    "pācay": 807,
    "vihā": 808,
    "inv": 809,
    "citay": 810,
    "marjay": 811,
    "manasy": 812,
    "viruh": 813,
    "vihvṛ": 814,
    "daṃś": 815,
    "ākhyā": 816,
    "viruc": 817,
    "atipad": 818,
    "upasamindh": 819,
    "saṃkalpay": 820,
    "unmuc": 821,
    "ramay": 822,
    "upamath": 823,
    "vyavasā": 824,
    "abhigam": 825,
    "vyaś": 826,
    "plu": 827,
    "nirdiś": 828,
    "saṃdah": 829,
    "apāvṛ": 830,
    "tṛd": 831,
    "bhas": 832,
    "nāth": 833,
    "hīḍ": 834,
    "pāday": 835,
    "pratye": 836,
    "saṃyaj": 837,
    "dohay": 838,
    "pratap": 839,
    "parimṛś": 840,
    "uddiś": 841,
    "anūtthā": 842,
    "vāday": 843,
    "āsthāpay": 844,
    "vimā": 845,
    "abhiyaj": 846,
    "āveday": 847,
    "samāgam": 848,
    "saṃyu": 849,
    "pratyavaruh": 850,
    "pramṛ": 851,
    "abhirakṣ": 852,
    "nirdah": 853,
    "ūh": 854,
    "apahṛ": 855,
    "kṣip": 856,
    "anvīkṣ": 857,
    "nirvah": 858,
    "nihnu": 859,
    "apisṛj": 860,
    "nirbhaj": 861,
    "upaninī": 862,
    "yopay": 863,
    "parye": 864,
    "bubhūṣ": 865,
    "uṣ": 866,
    "mohay": 867,
    "dṛp": 868,
    "day": 869,
    "ādhṛṣ": 870,
    "śṛdh": 871,
    "vihan": 872,
    "yāvay": 873,
    "nikram": 874,
    "pratyāhan": 875,
    "dīkṣay": 876,
    "atyṛj": 877,
    "praji": 878,
    "pratyabhimṛś": 879,
    "ālikh": 880,
    "upabrū": 881,
    "parivraj": 882,
    "udvah": 883,
    "eray": 884,
    "utkṛt": 885,
    "viśas": 886,
    "anulip": 887,
    "ākramay": 888,
    "nirvac": 889,
    "vivṛ": 890,
    "anubudh": 891,
    "veday": 892,
    "ādīp": 893,
    "bhāvay": 894,
    "mantray": 895,
    "adhijan": 896,
    "upāv": 897,
    "ārch": 898,
    "parīvṛ": 899,
    "dodhu": 900,
    "myakṣ": 901,
    "tuj": 902,
    "viṣ": 903,
    "dṛ": 904,
    "vāray": 905,
    "paty": 906,
    "vidhū": 907,
    "bhājay": 908,
    "abhivṛt": 909,
    "saṃveśay": 910,
    "samāhṛ": 911,
    "mṛś": 912,
    "saṃrabh": 913,
    "pariveviṣ": 914,
    "adhinidhā": 915,
    "niviś": 916,
    "abhisaṃbhṛ": 917,
    "nirmuc": 918,
    "ādīpay": 919,
    "ātañc": 920,
    "apākṛ": 921,
    "triṣphalīkṛ": 922,
    "adhyūh": 923,
    "vicar": 924,
    "āmay": 925,
    "vivac": 926,
    "āhāray": 927,
    "upakram": 928,
    "vyāghāray": 929,
    "samāvap": 930,
    "apekṣ": 931,
    "upanah": 932,
    "parivah": 933,
    "anuprajñā": 934,
    "viśās": 935,
    "parābhū": 936,
    "udānī": 937,
    "cikīrṣ": 938,
    "paripā": 939,
    "parikrī": 940,
    "vipravas": 941,
    "niveday": 942,
    "avahan": 943,
    "saṃkhyā": 944,
    "upapad": 945,
    "saṃniviś": 946,
    "saṃdṛś": 947,
    "prapat": 948,
    "saṃyam": 949,
    "dī": 950,
    "gur": 951,
    "sphur": 952,
    "viśru": 953,
    "upāvahṛ": 954,
    "upapreṣ": 955,
    "nimruc": 956,
    "abhipre": 957,
    "ārohay": 958,
    "abhye": 959,
    "avanenij": 960,
    "pratikṛ": 961,
    "nivartay": 962,
    "pratihan": 963,
    "āci": 964,
    "majj": 965,
    "parīkṣ": 966,
    "sañj": 967,
    "chāday": 968,
    "abhivīkṣ": 969,
    "pradiś": 970,
    "nipad": 971,
    "cāy": 972,
    "abhivikhyā": 973,
    "garh": 974,
    "pratiṣidh": 975,
    "apanud": 976,
    "niveśay": 977,
    "ghrā": 978,
    "abhivyāhṛ": 979,
    "khād": 980,
    "atiśiṣ": 981,
    "lī": 982,
    "apikṛt": 983,
    "āhan": 984,
    "abhyāruh": 985,
    "saṃstu": 986,
    "vidyut": 987,
    "udaj": 988,
    "samādā": 989,
    "ārudh": 990,
    "āśī": 991,
    "tud": 992,
    "purodhā": 993,
    "īṣ": 994,
    "riṣaṇy": 995,
    "nādh": 996,
    "rohay": 997,
    "ghṛ": 998,
    "unmaday": 999,
    "pracyu": 1000,
    "anugamay": 1001,
    "ādru": 1002,
    "prave": 1003,
    "atiman": 1004,
    "adhyāpay": 1005,
    "paritan": 1006,
    "namaskṛ": 1007,
    "pramṛj": 1008,
    "abhinidhā": 1009,
    "utsṛp": 1010,
    "anukram": 1011,
    "miṣ": 1012,
    "niḥṣṭhā": 1013,
    "avakram": 1014,
    "prasṛj": 1015,
    "upaniṣkram": 1016,
    "vāvad": 1017,
    "upasthāpay": 1018,
    "samas": 1019,
    "saṃkṣar": 1020,
    "vikṣar": 1021,
    "ātṛd": 1022,
    "jakṣ": 1023,
    "upajan": 1024,
    "śvi": 1025,
    "jñapay": 1026,
    "nigam": 1027,
    "parivṛt": 1028,
    "uccar": 1029,
    "abhikram": 1030,
    "anumṛj": 1031,
    "ave": 1032,
    "piś": 1033,
    "sas": 1034,
    "jaray": 1035,
    "nas": 1036,
    "mṛṣ": 1037,
    "saṃtṛ": 1038,
    "udīr": 1039,
    "āśuṣ": 1040,
    "nij": 1041,
    "cātay": 1042,
    "davidyut": 1043,
    "ven": 1044,
    "vivṛt": 1045,
    "apaguh": 1046,
    "viśudh": 1047,
    "arcay": 1048,
    "namasy": 1049,
    "pratibrū": 1050,
    "śatrūy": 1051,
    "āsyand": 1052,
    "duvasy": 1053,
    "avagrah": 1054,
    "samāpay": 1055,
    "pratyuddīp": 1056,
    "jugups": 1057,
    "saṃvraśc": 1058,
    "pratyad": 1059,
    "preray": 1060,
    "vipaś": 1061,
    "ślāgh": 1062,
    "udīkṣ": 1063,
    "avagāh": 1064,
    "paricakṣ": 1065,
    "adhisṛj": 1066,
    "anubandh": 1067,
    "saṃvas": 1068,
    "pratyañj": 1069,
    "dam": 1070,
    "śrāvay": 1071,
    "parāsic": 1072,
    "āvyadh": 1073,
    "anugrah": 1074,
    "muṣ": 1075,
    "nicāy": 1076,
    "vīkṣ": 1077,
    "samudūh": 1078,
    "atikṣar": 1079,
    "niṣkṛ": 1080,
    "udbhṛ": 1081,
    "sādhay": 1082,
    "avatan": 1083,
    "atisṛp": 1084,
    "saṃji": 1085,
    "anusaṃcar": 1086,
    "bhañj": 1087,
    "cṛt": 1088,
    "lips": 1089,
    "avadyotay": 1090,
    "vyāvartay": 1091,
    "joṣay": 1092,
    "parāvadh": 1093,
    "avās": 1094,
    "pratyāgam": 1095,
    "abhisambhū": 1096,
    "āpūray": 1097,
    "abhibhāṣ": 1098,
    "vimṛj": 1099,
    "ālip": 1100,
    "parikṛ": 1101,
    "ācamay": 1102,
    "prak￞": 1103,
    "abhyund": 1104,
    "pravap": 1105,
    "pramuṣ": 1106,
    "āgamay": 1107,
    "māpay": 1108,
    "upayā": 1109,
    "druh": 1110,
    "prahā": 1111,
    "upakﾱp": 1112,
    "āñc": 1113,
    "anvavahṛ": 1114,
    "pradhā": 1115,
    "anudiś": 1116,
    "saṃvye": 1117,
    "pratyas": 1118,
    "prakṣip": 1119,
    "abhyutthā": 1120,
    "nimā": 1121,
    "mṛdh": 1122,
    "āyat": 1123,
    "chad": 1124,
    "tāray": 1125,
    "abhiṣu": 1126,
    "samāropay": 1127,
    "atinī": 1128,
    "praśam": 1129,
    "apaji": 1130,
    "avakalpay": 1131,
    "tirodhā": 1132,
    "apacchid": 1133,
    "avabādh": 1134,
    "paryṛṣ": 1135,
    "anūtpā": 1136,
    "kṣam": 1137,
    "uparudh": 1138,
    "upokṣ": 1139,
    "pāvay": 1140,
    "pratyācakṣ": 1141,
    "bhūṣ": 1142,
    "abhivraj": 1143,
    "āyaj": 1144,
    "daśasy": 1145,
    "jarbhur": 1146,
    "vihvā": 1147,
    "jambhay": 1148,
    "ubj": 1149,
    "ujjhā": 1150,
    "nonāv": 1151,
    "jas": 1152,
    "abhidruh": 1153,
    "svaj": 1154,
    "hṛṣ": 1155,
    "nistakṣ": 1156,
    "pratīṣ": 1157,
    "rup": 1158,
    "vij": 1159,
    "saṃsāday": 1160,
    "anuvaṣaṭkṛ": 1161,
    "āprī": 1162,
    "paryas": 1163,
    "anvāgam": 1164,
    "udavasā": 1165,
    "vigrah": 1166,
    "bībhats": 1167,
    "anuninī": 1168,
    "dhīps": 1169,
    "pratyavekṣ": 1170,
    "pradāpay": 1171,
    "vyāpad": 1172,
    "upādhā": 1173,
    "samāmnā": 1174,
    "āvirbhū": 1175,
    "upapre": 1176,
    "vlī": 1177,
    "krūḍay": 1178,
    "parisaṃvah": 1179,
    "samprokṣ": 1180,
    "ācāmay": 1181,
    "prāduṣkṛ": 1182,
    "prasāray": 1183,
    "kṣu": 1184,
    "nimi": 1185,
    "pratijñā": 1186,
    "atigāh": 1187,
    "anvavamṛś": 1188,
    "upaguh": 1189,
    "apabādh": 1190,
    "pṛtanāy": 1191,
    "upadru": 1192,
    "apigrah": 1193,
    "anuvyākhyā": 1194,
    "apipad": 1195,
    "ativṛdh": 1196,
    "nirvṛt": 1197,
    "anūdi": 1198,
    "āvraj": 1199,
    "pragrah": 1200,
    "śuśrūṣ": 1201,
    "tak": 1202,
    "ghuṣ": 1203,
    "apavṛ": 1204,
    "śośuc": 1205,
    "nind": 1206,
    "chanday": 1207,
    "chand": 1208,
    "bhuraṇy": 1209,
    "abhicākaś": 1210,
    "vyavacchid": 1211,
    "durasy": 1212,
    "an": 1213,
    "khid": 1214,
    "vyṛṣ": 1215,
    "uc": 1216,
    "arday": 1217,
    "acchāvad": 1218,
    "abhivah": 1219,
    "vivyadh": 1220,
    "sampariśri": 1221,
    "anūde": 1222,
    "vivṛh": 1223,
    "prajñāpay": 1224,
    "ākranday": 1225,
    "udañc": 1226,
    "nirjñā": 1227,
    "sampṛ": 1228,
    "paryāhṛ": 1229,
    "praskanday": 1230,
    "saṃvap": 1231,
    "abhyāgam": 1232,
    "upaghrā": 1233,
    "niḥsāray": 1234,
    "adhyavaso": 1235,
    "prasad": 1236,
    "udas": 1237,
    "sīv": 1238,
    "pratigṛ": 1239,
    "saṃgā": 1240,
    "parivad": 1241,
    "anvañj": 1242,
    "upaśī": 1243,
    "āccho": 1244,
    "apās": 1245,
    "upatṛd": 1246,
    "apamṛj": 1247,
    "pratyāvraj": 1248,
    "prajval": 1249,
    "nigṛ": 1250,
    "pratāpay": 1251,
    "pravartay": 1252,
    "prahas": 1253,
    "tuṣ": 1254,
    "prasnā": 1255,
    "prāvṛ": 1256,
    "abhighrā": 1257,
    "pariplu": 1258,
    "cetay": 1259,
    "samās": 1260,
    "vyāp": 1261,
    "viparyas": 1262,
    "vikṛṣ": 1263,
    "vigam": 1264,
    "ābhaj": 1265,
    "āpay": 1266,
    "prer": 1267,
    "paripaś": 1268,
    "vivad": 1269,
    "śnath": 1270,
    "anumad": 1271,
    "saṃhā": 1272,
    "er": 1273,
    "si": 1274,
    "mṛgay": 1275,
    "vici": 1276,
    "ākṛ": 1277,
    "pramud": 1278,
    "īṅkhay": 1279,
    "saṃyājay": 1280,
    "yātay": 1281,
    "sampāday": 1282,
    "ścut": 1283,
    "vimath": 1284,
    "upaśam": 1285,
    "ākāṅkṣ": 1286,
    "pratyānī": 1287,
    "vyutkram": 1288,
    "upāvanam": 1289,
    "avān": 1290,
    "parikṛṣ": 1291,
    "unnabhay": 1292,
    "atihā": 1293,
    "abhibhū": 1294,
    "avanij": 1295,
    "utsāday": 1296,
    "mūrchay": 1297,
    "saṃkṛṣ": 1298,
    "vidah": 1299,
    "sambhid": 1300,
    "saṃvah": 1301,
    "marcay": 1302,
    "upanāmay": 1303,
    "plāvay": 1304,
    "kāṅkṣ": 1305,
    "udāyu": 1306,
    "satkṛ": 1307,
    "kathay": 1308,
    "upāghrā": 1309,
    "anujñāpay": 1310,
    "vimṛś": 1311,
    "saṃśri": 1312,
    "upādā": 1313,
    "cintay": 1314,
    "anuṣañj": 1315,
    "paribādh": 1316,
    "vilāpay": 1317,
    "adhijāgṛ": 1318,
    "samanvārabh": 1319,
    "hāray": 1320,
    "prakṛṣ": 1321,
    "praticchad": 1322,
    "avaghrā": 1323,
    "nyas": 1324,
    "samārohay": 1325,
    "ucchid": 1326,
    "vyavasthā": 1327,
    "saṃhṛ": 1328,
    "māray": 1329,
    "pradih": 1330,
    "vyañj": 1331,
    "samprasru": 1332,
    "atiśī": 1333,
    "diś": 1334,
    "vijñāpay": 1335,
    "upalabh": 1336,
    "pratṛ": 1337,
    "lelāy": 1338,
    "anubhā": 1339,
    "abhyavahṛ": 1340,
    "haviṣkṛ": 1341,
    "śuṣ": 1342,
    "avabhṛ": 1343,
    "anusaṃsthā": 1344,
    "anuparī": 1345,
    "upavap": 1346,
    "āvay": 1347,
    "anuśaṃs": 1348,
    "tsar": 1349,
    "avacchid": 1350,
    "apyas": 1351,
    "mih": 1352,
    "anujan": 1353,
    "vinaś": 1354,
    "vinidhā": 1355,
    "āśaṃs": 1356,
    "apigam": 1357,
    "uparam": 1358,
    "nirvid": 1359,
    "apadru": 1360,
    "dhāvay": 1361,
    "anuprāṇ": 1362,
    "āj": 1363,
    "vṛṣāy": 1364,
    "raṃh": 1365,
    "ṛtāy": 1366,
    "dits": 1367,
    "brahmaṇy": 1368,
    "iyakṣ": 1369,
    "vicṛt": 1370,
    "gṛbhāy": 1371,
    "cekit": 1372,
    "yodhay": 1373,
    "viyu": 1374,
    "sridh": 1375,
    "dakṣ": 1376,
    "prakhyā": 1377,
    "chaday": 1378,
    "ribh": 1379,
    "vīḍay": 1380,
    "tuś": 1381,
    "tviṣ": 1382,
    "rap": 1383,
    "vip": 1384,
    "saṃpaś": 1385,
    "pruṣāy": 1386,
    "apacyu": 1387,
    "jaṅghan": 1388,
    "saṃśṛ": 1389,
    "do": 1390,
    "apinah": 1391,
    "āñj": 1392,
    "abhidhyai": 1393,
    "anunirvap": 1394,
    "apagā": 1395,
    "jijyūṣ": 1396,
    "apapravas": 1397,
    "utsic": 1398,
    "adhyas": 1399,
    "anvavadhā": 1400,
    "parāpū": 1401,
    "vivic": 1402,
    "abhisṛp": 1403,
    "parive": 1404,
    "paryālabh": 1405,
    "apidah": 1406,
    "avayaj": 1407,
    "upavājay": 1408,
    "paryañj": 1409,
    "pratiparī": 1410,
    "parākram": 1411,
    "tvar": 1412,
    "samāruh": 1413,
    "varṣay": 1414,
    "upavāsay": 1415,
    "abhipravah": 1416,
    "vikhid": 1417,
    "pratikhyā": 1418,
    "abhiduh": 1419,
    "nirvad": 1420
  },
  "index_to_lemma": [
    "kṛ",
    "bhū",
    "vid",
    "hu",
    "as",
    "yaj",
    "ah",
    "vac",
    "dhā",
    "i",
    "jan",
    "gam",
    "brū",
    "dā",
    "grah",
    "sthā",
    "pā",
    "sṛj",
    "ālabh",
    "car",
    "ādhā",
    "pū",
    "ādā",
    "han",
    "nidhā",
    "bhṛ",
    "paś",
    "yuj",
    "śru",
    "pratiṣṭhā",
    "vad",
    "upās",
    "ji",
    "āp",
    "aś",
    "hvā",
    "gā",
    "e",
    "vṛ",
    "yā",
    "dṛś",
    "añj",
    "su",
    "man",
    "juṣ",
    "iṣ",
    "hṛ",
    "av",
    "nī",
    "kāmay",
    "ās",
    "pṛ",
    "āgam",
    "vah",
    "stu",
    "jap",
    "tap",
    "duh",
    "upasthā",
    "yam",
    "udi",
    "muc",
    "upe",
    "āhṛ",
    "praviś",
    "nirvap",
    "jīv",
    "prayam",
    "avarudh",
    "vas",
    "anvah",
    "anubrū",
    "upahvā",
    "prāś",
    "vṛdh",
    "prī",
    "hiṃs",
    "sambhū",
    "dviṣ",
    "prajan",
    "sambhṛ",
    "prokṣ",
    "samṛdh",
    "apahan",
    "ad",
    "pracch",
    "tṛ",
    "math",
    "sad",
    "janay",
    "bandh",
    "praṇī",
    "pre",
    "jñā",
    "upaviś",
    "dhāray",
    "utkram",
    "dīkṣ",
    "vijñā",
    "hā",
    "paridhā",
    "ācakṣ",
    "adhī",
    "vaś",
    "pratigrah",
    "īś",
    "tan",
    "vī",
    "utthā",
    "samardhay",
    "prahṛ",
    "bhuj",
    "śaṃs",
    "bhī",
    "khan",
    "anumantray",
    "rakṣ",
    "abhimantray",
    "sic",
    "prayuj",
    "anuvac",
    "pratiṣṭhāpay",
    "āruh",
    "chid",
    "dṛh",
    "prapad",
    "parigrah",
    "ci",
    "gṛ",
    "naś",
    "śrapay",
    "prasū",
    "sah",
    "upaspṛś",
    "snā",
    "bhid",
    "āgā",
    "sampad",
    "kṣi",
    "prajñā",
    "āśās",
    "śak",
    "anuvical",
    "indh",
    "mad",
    "śudh",
    "ānī",
    "sac",
    "pratipad",
    "samindh",
    "vṛt",
    "ṛch",
    "upadhāv",
    "cit",
    "hi",
    "mṛ",
    "kāray",
    "śam",
    "ācam",
    "āvap",
    "ucchri",
    "vyadh",
    "ninī",
    "udgā",
    "saṃpreṣ",
    "kalpay",
    "dhṛ",
    "śī",
    "sāday",
    "uddhṛ",
    "abhimṛś",
    "vardhay",
    "īḍ",
    "ārabh",
    "prāp",
    "gopāy",
    "saṃsṛj",
    "ruh",
    "tṛp",
    "abhighāray",
    "āviś",
    "prajanay",
    "dhyā",
    "ṛdh",
    "jinv",
    "ruc",
    "upadhā",
    "prakṣālay",
    "pac",
    "stṛ",
    "śri",
    "vyākhyā",
    "sammṛj",
    "tarpay",
    "unnī",
    "ī",
    "avado",
    "saṃdhā",
    "vap",
    "adhiśri",
    "vācay",
    "kﾱp",
    "viś",
    "dāś",
    "pat",
    "bhakṣay",
    "avadhā",
    "dah",
    "vraśc",
    "gamay",
    "parī",
    "anvārabh",
    "saṃsthā",
    "ram",
    "utsṛj",
    "abhihu",
    "antardhā",
    "upākṛ",
    "upavas",
    "pradā",
    "vṛj",
    "śrī",
    "riṣ",
    "trā",
    "atī",
    "saṃskṛ",
    "pravac",
    "nam",
    "mā",
    "prāṇ",
    "nud",
    "utthāpay",
    "abhyukṣ",
    "yājay",
    "pad",
    "krand",
    "labh",
    "apakram",
    "alaṃkṛ",
    "upajīv",
    "śram",
    "paridā",
    "apī",
    "īkṣ",
    "sṛ",
    "kṣar",
    "pinv",
    "jṛ",
    "upasamādhā",
    "abhyādhā",
    "svap",
    "upastṛ",
    "nivap",
    "atiric",
    "sidh",
    "kram",
    "yāc",
    "abhivad",
    "udyam",
    "pāyay",
    "udvāsay",
    "pratimuc",
    "avekṣ",
    "atikram",
    "anvi",
    "dhāv",
    "pyā",
    "āvṛt",
    "upasṛ",
    "takṣ",
    "saṃmā",
    "anuman",
    "prath",
    "āpyā",
    "preṣ",
    "parilikh",
    "parivye",
    "paristṛ",
    "āmantray",
    "saṃjñapay",
    "śamay",
    "rādh",
    "niyuj",
    "pramuc",
    "mi",
    "anugam",
    "ācchṛd",
    "upaveśay",
    "dīdī",
    "rā",
    "śās",
    "pare",
    "nikhan",
    "svad",
    "parihṛ",
    "abhitap",
    "praśaṃs",
    "arc",
    "abhipad",
    "mṛj",
    "āsad",
    "abhicar",
    "rocay",
    "upasāday",
    "niras",
    "apidhā",
    "bādh",
    "jval",
    "ābhṛ",
    "bhrāj",
    "mī",
    "abhyañj",
    "pūray",
    "yu",
    "māday",
    "bhaj",
    "devay",
    "bhā",
    "ṛṣ",
    "van",
    "vājay",
    "śubh",
    "āvah",
    "visṛj",
    "upasad",
    "prabrū",
    "āśrāvay",
    "utpū",
    "pravas",
    "bhojay",
    "saṃcar",
    "śuc",
    "budh",
    "yat",
    "āpyāyay",
    "abhiṣic",
    "sammṛś",
    "vimuc",
    "paryūh",
    "parāpat",
    "upadiś",
    "avasic",
    "varjay",
    "anuvid",
    "saṃvid",
    "puṣ",
    "cakṣ",
    "vidh",
    "nū",
    "guh",
    "san",
    "dīv",
    "nah",
    "ādṛ",
    "āsāday",
    "krī",
    "anuprahṛ",
    "spṛdh",
    "sṛp",
    "dhū",
    "vivakṣ",
    "pracchid",
    "visraṃs",
    "gras",
    "skand",
    "pṛṇ",
    "syand",
    "vitan",
    "vṛṣ",
    "vadh",
    "pariśri",
    "atimuc",
    "bhāṣ",
    "upanam",
    "āpad",
    "upagā",
    "vidhā",
    "āstṛ",
    "adhiruh",
    "upahan",
    "sru",
    "adhivah",
    "vibhā",
    "yudh",
    "sū",
    "nāśay",
    "upayam",
    "spṛś",
    "niṣad",
    "nirmath",
    "saṃyuj",
    "coday",
    "dhṛṣ",
    "ādiś",
    "samañj",
    "nivṛt",
    "anvāyat",
    "pramad",
    "mahīy",
    "jāgṛ",
    "mṛḍ",
    "ape",
    "gup",
    "vyṛdh",
    "saṃśā",
    "pratyah",
    "anudru",
    "paryagnikṛ",
    "vyath",
    "pratiṣic",
    "ākram",
    "parikram",
    "samāp",
    "anujñā",
    "prapāday",
    "āsthā",
    "dīp",
    "vikṛ",
    "saṃvad",
    "saṃnī",
    "prāśay",
    "bhikṣ",
    "īray",
    "īr",
    "śikṣ",
    "stanay",
    "upāp",
    "antari",
    "prāh",
    "arpay",
    "prastu",
    "prekṣ",
    "rud",
    "vartay",
    "vyāvṛt",
    "viriṣ",
    "dhūpay",
    "anuṣṭhā",
    "atisṛj",
    "nimṛj",
    "upalip",
    "niṣkram",
    "pratitap",
    "vihṛ",
    "avokṣ",
    "anuśās",
    "apān",
    "pramī",
    "pṛc",
    "pariśiṣ",
    "vyāhṛ",
    "mārjay",
    "ude",
    "pravṛ",
    "arh",
    "abhiji",
    "ācar",
    "paryukṣ",
    "ukṣ",
    "pratī",
    "saṃnah",
    "pracchāday",
    "samutthā",
    "lip",
    "anusṛj",
    "saṃtan",
    "ric",
    "dham",
    "kṛṣ",
    "vand",
    "dru",
    "krīḍ",
    "kanikrad",
    "vikram",
    "āyam",
    "piṣ",
    "vibhaj",
    "ājan",
    "avaruh",
    "vyūh",
    "saṃkﾱp",
    "vaṣaṭkṛ",
    "unmṛj",
    "avāp",
    "pratidhā",
    "upāvṛt",
    "stambh",
    "upasṛj",
    "vipat",
    "śā",
    "chṛd",
    "āśay",
    "ullikh",
    "vāś",
    "pariṣic",
    "uddhan",
    "saṃviś",
    "pṛtany",
    "pravṛj",
    "arātīy",
    "jū",
    "sā",
    "āhu",
    "ghas",
    "pariṣvaj",
    "pravah",
    "dhūrv",
    "grāhay",
    "vyācakṣ",
    "pratan",
    "prās",
    "kṛt",
    "avasṛj",
    "abhiśaṃs",
    "avaguh",
    "parimā",
    "praṇud",
    "abhipīḍay",
    "und",
    "parisamūh",
    "saṃhan",
    "ucchiṣ",
    "vivas",
    "abhyudi",
    "āvṛ",
    "bodhay",
    "ej",
    "pariṣkṛ",
    "dhī",
    "randhay",
    "parāji",
    "prasthā",
    "samavado",
    "saṃsthāpay",
    "upasaṃgrah",
    "āsic",
    "tyaj",
    "pracar",
    "adhiṣṭhā",
    "prathay",
    "adhigam",
    "tṛṣ",
    "ri",
    "vye",
    "abhidhā",
    "niṣkrī",
    "kīrtay",
    "sami",
    "udvap",
    "śṛ",
    "parāmṛś",
    "ābandh",
    "vicchid",
    "pariṇī",
    "avasthāpay",
    "mud",
    "muh",
    "anviṣ",
    "bhiṣajy",
    "udgrah",
    "vigā",
    "rih",
    "uruṣy",
    "ruj",
    "khyā",
    "mṛḍay",
    "nakṣ",
    "āvāhay",
    "śraddhā",
    "acchāi",
    "ācchid",
    "nirmā",
    "udūh",
    "pradah",
    "upanidhā",
    "āvartay",
    "rāj",
    "mah",
    "rabh",
    "rudh",
    "sampṛc",
    "duṣ",
    "abhivāday",
    "viṣṭhā",
    "āyā",
    "ātan",
    "cyu",
    "anūpasthā",
    "jighṛkṣay",
    "saṃspṛś",
    "vraj",
    "pravṛt",
    "abhyāvṛt",
    "prahi",
    "samīkṣ",
    "ve",
    "avastṛ",
    "dhi",
    "vibhū",
    "johav",
    "vā",
    "siṣās",
    "niyam",
    "spṛ",
    "krudh",
    "saṃgam",
    "svaday",
    "saṃtap",
    "āhvā",
    "atihṛ",
    "prayā",
    "nirūh",
    "avaśiṣ",
    "abhyave",
    "āplāvay",
    "pratīkṣ",
    "upanī",
    "abhīndh",
    "upavad",
    "avanī",
    "āpṛṇ",
    "niṣṭap",
    "īps",
    "pratyuṣ",
    "saṃnam",
    "samaś",
    "pravad",
    "paryāvṛt",
    "pratyāśrāvay",
    "vyardhay",
    "upotthā",
    "avasthā",
    "prasṛ",
    "āghāray",
    "pratinand",
    "ācchāday",
    "abhiṣṭhā",
    "pratyūh",
    "upamantray",
    "iṣay",
    "rad",
    "vakṣ",
    "ru",
    "abhivac",
    "pravṛh",
    "abhyāyam",
    "utkhid",
    "likh",
    "vinī",
    "arhay",
    "samādhā",
    "abhyupe",
    "udāhṛ",
    "smṛ",
    "same",
    "ran",
    "cyāvay",
    "dips",
    "vyatiṣañj",
    "vāsay",
    "pratyabhighāray",
    "pūjay",
    "saṃnidhā",
    "paridhāpay",
    "radh",
    "upagrah",
    "anubhū",
    "viji",
    "saṃsparśay",
    "nirbhid",
    "abhidru",
    "ativah",
    "dyut",
    "ābhū",
    "upacar",
    "praṇed",
    "viṣā",
    "paricar",
    "parimṛj",
    "saṃgrah",
    "parivṛ",
    "upahu",
    "saṃśās",
    "snāpay",
    "sambhāṣ",
    "hiṃkṛ",
    "pratihṛ",
    "upagam",
    "niṣṭhā",
    "dih",
    "ceṣṭ",
    "marmṛj",
    "pratibudh",
    "jyā",
    "āve",
    "pātay",
    "abhī",
    "hary",
    "aj",
    "hvṛ",
    "nihan",
    "saṃyat",
    "upakalpay",
    "anvādhā",
    "abhijan",
    "lū",
    "abhiṣṭu",
    "pralip",
    "pariviṣ",
    "vāpay",
    "anugā",
    "śiṣ",
    "anupraviś",
    "rej",
    "mand",
    "prāv",
    "pravid",
    "sthāpay",
    "roro",
    "sapary",
    "kan",
    "āvraśc",
    "ārpay",
    "parivṛj",
    "āvad",
    "prasic",
    "darśay",
    "pīḍay",
    "nigrah",
    "samprayam",
    "prahu",
    "upahṛ",
    "saṃstṛ",
    "prabhū",
    "pāray",
    "jighāṃs",
    "sādh",
    "vṛh",
    "dabh",
    "utprayam",
    "ujji",
    "śap",
    "prakram",
    "pratimantray",
    "prabandh",
    "upālabh",
    "vijijiñās",
    "āplu",
    "saṃjñā",
    "jigīṣ",
    "tam",
    "avadhū",
    "nirmṛj",
    "nand",
    "avasā",
    "uddru",
    "vyākṛ",
    "samānī",
    "pratyākram",
    "prayu",
    "parivāsay",
    "pradru",
    "abhisampad",
    "abhigā",
    "nigad",
    "samupāśri",
    "abhidās",
    "vivās",
    "gāh",
    "patay",
    "upamṛj",
    "upayuj",
    "prādurbhū",
    "anuprajan",
    "pragā",
    "praveṣṭay",
    "virāj",
    "prāpay",
    "abhijñā",
    "vidhvaṃs",
    "samāvṛt",
    "sammi",
    "abhisaṃviś",
    "mahay",
    "anupaś",
    "nilip",
    "yavay",
    "prā",
    "nirudh",
    "ṛj",
    "smi",
    "dhanv",
    "svar",
    "mṛṇ",
    "aparudh",
    "avakṛ",
    "anugup",
    "mīmāṃs",
    "edh",
    "samave",
    "avapad",
    "abhipravraj",
    "pravraj",
    "saṃvṛt",
    "abhiman",
    "abhikṣar",
    "abhiprāṇ",
    "pācay",
    "vihā",
    "inv",
    "citay",
    "marjay",
    "manasy",
    "viruh",
    "vihvṛ",
    "daṃś",
    "ākhyā",
    "viruc",
    "atipad",
    "upasamindh",
    "saṃkalpay",
    "unmuc",
    "ramay",
    "upamath",
    "vyavasā",
    "abhigam",
    "vyaś",
    "plu",
    "nirdiś",
    "saṃdah",
    "apāvṛ",
    "tṛd",
    "bhas",
    "nāth",
    "hīḍ",
    "pāday",
    "pratye",
    "saṃyaj",
    "dohay",
    "pratap",
    "parimṛś",
    "uddiś",
    "anūtthā",
    "vāday",
    "āsthāpay",
    "vimā",
    "abhiyaj",
    "āveday",
    "samāgam",
    "saṃyu",
    "pratyavaruh",
    "pramṛ",
    "abhirakṣ",
    "nirdah",
    "ūh",
    "apahṛ",
    "kṣip",
    "anvīkṣ",
    "nirvah",
    "nihnu",
    "apisṛj",
    "nirbhaj",
    "upaninī",
    "yopay",
    "parye",
    "bubhūṣ",
    "uṣ",
    "mohay",
    "dṛp",
    "day",
    "ādhṛṣ",
    "śṛdh",
    "vihan",
    "yāvay",
    "nikram",
    "pratyāhan",
    "dīkṣay",
    "atyṛj",
    "praji",
    "pratyabhimṛś",
    "ālikh",
    "upabrū",
    "parivraj",
    "udvah",
    "eray",
    "utkṛt",
    "viśas",
    "anulip",
    "ākramay",
    "nirvac",
    "vivṛ",
    "anubudh",
    "veday",
    "ādīp",
    "bhāvay",
    "mantray",
    "adhijan",
    "upāv",
    "ārch",
    "parīvṛ",
    "dodhu",
    "myakṣ",
    "tuj",
    "viṣ",
    "dṛ",
    "vāray",
    "paty",
    "vidhū",
    "bhājay",
    "abhivṛt",
    "saṃveśay",
    "samāhṛ",
    "mṛś",
    "saṃrabh",
    "pariveviṣ",
    "adhinidhā",
    "niviś",
    "abhisaṃbhṛ",
    "nirmuc",
    "ādīpay",
    "ātañc",
    "apākṛ",
    "triṣphalīkṛ",
    "adhyūh",
    "vicar",
    "āmay",
    "vivac",
    "āhāray",
    "upakram",
    "vyāghāray",
    "samāvap",
    "apekṣ",
    "upanah",
    "parivah",
    "anuprajñā",
    "viśās",
    "parābhū",
    "udānī",
    "cikīrṣ",
    "paripā",
    "parikrī",
    "vipravas",
    "niveday",
    "avahan",
    "saṃkhyā",
    "upapad",
    "saṃniviś",
    "saṃdṛś",
    "prapat",
    "saṃyam",
    "dī",
    "gur",
    "sphur",
    "viśru",
    "upāvahṛ",
    "upapreṣ",
    "nimruc",
    "abhipre",
    "ārohay",
    "abhye",
    "avanenij",
    "pratikṛ",
    "nivartay",
    "pratihan",
    "āci",
    "majj",
    "parīkṣ",
    "sañj",
    "chāday",
    "abhivīkṣ",
    "pradiś",
    "nipad",
    "cāy",
    "abhivikhyā",
    "garh",
    "pratiṣidh",
    "apanud",
    "niveśay",
    "ghrā",
    "abhivyāhṛ",
    "khād",
    "atiśiṣ",
    "lī",
    "apikṛt",
    "āhan",
    "abhyāruh",
    "saṃstu",
    "vidyut",
    "udaj",
    "samādā",
    "ārudh",
    "āśī",
    "tud",
    "purodhā",
    "īṣ",
    "riṣaṇy",
    "nādh",
    "rohay",
    "ghṛ",
    "unmaday",
    "pracyu",
    "anugamay",
    "ādru",
    "prave",
    "atiman",
    "adhyāpay",
    "paritan",
    "namaskṛ",
    "pramṛj",
    "abhinidhā",
    "utsṛp",
    "anukram",
    "miṣ",
    "niḥṣṭhā",
    "avakram",
    "prasṛj",
    "upaniṣkram",
    "vāvad",
    "upasthāpay",
    "samas",
    "saṃkṣar",
    "vikṣar",
    "ātṛd",
    "jakṣ",
    "upajan",
    "śvi",
    "jñapay",
    "nigam",
    "parivṛt",
    "uccar",
    "abhikram",
    "anumṛj",
    "ave",
    "piś",
    "sas",
    "jaray",
    "nas",
    "mṛṣ",
    "saṃtṛ",
    "udīr",
    "āśuṣ",
    "nij",
    "cātay",
    "davidyut",
    "ven",
    "vivṛt",
    "apaguh",
    "viśudh",
    "arcay",
    "namasy",
    "pratibrū",
    "śatrūy",
    "āsyand",
    "duvasy",
    "avagrah",
    "samāpay",
    "pratyuddīp",
    "jugups",
    "saṃvraśc",
    "pratyad",
    "preray",
    "vipaś",
    "ślāgh",
    "udīkṣ",
    "avagāh",
    "paricakṣ",
    "adhisṛj",
    "anubandh",
    "saṃvas",
    "pratyañj",
    "dam",
    "śrāvay",
    "parāsic",
    "āvyadh",
    "anugrah",
    "muṣ",
    "nicāy",
    "vīkṣ",
    "samudūh",
    "atikṣar",
    "niṣkṛ",
    "udbhṛ",
    "sādhay",
    "avatan",
    "atisṛp",
    "saṃji",
    "anusaṃcar",
    "bhañj",
    "cṛt",
    "lips",
    "avadyotay",
    "vyāvartay",
    "joṣay",
    "parāvadh",
    "avās",
    "pratyāgam",
    "abhisambhū",
    "āpūray",
    "abhibhāṣ",
    "vimṛj",
    "ālip",
    "parikṛ",
    "ācamay",
    "prak￞",
    "abhyund",
    "pravap",
    "pramuṣ",
    "āgamay",
    "māpay",
    "upayā",
    "druh",
    "prahā",
    "upakﾱp",
    "āñc",
    "anvavahṛ",
    "pradhā",
    "anudiś",
    "saṃvye",
    "pratyas",
    "prakṣip",
    "abhyutthā",
    "nimā",
    "mṛdh",
    "āyat",
    "chad",
    "tāray",
    "abhiṣu",
    "samāropay",
    "atinī",
    "praśam",
    "apaji",
    "avakalpay",
    "tirodhā",
    "apacchid",
    "avabādh",
    "paryṛṣ",
    "anūtpā",
    "kṣam",
    "uparudh",
    "upokṣ",
    "pāvay",
    "pratyācakṣ",
    "bhūṣ",
    "abhivraj",
    "āyaj",
    "daśasy",
    "jarbhur",
    "vihvā",
    "jambhay",
    "ubj",
    "ujjhā",
    "nonāv",
    "jas",
    "abhidruh",
    "svaj",
    "hṛṣ",
    "nistakṣ",
    "pratīṣ",
    "rup",
    "vij",
    "saṃsāday",
    "anuvaṣaṭkṛ",
    "āprī",
    "paryas",
    "anvāgam",
    "udavasā",
    "vigrah",
    "bībhats",
    "anuninī",
    "dhīps",
    "pratyavekṣ",
    "pradāpay",
    "vyāpad",
    "upādhā",
    "samāmnā",
    "āvirbhū",
    "upapre",
    "vlī",
    "krūḍay",
    "parisaṃvah",
    "samprokṣ",
    "ācāmay",
    "prāduṣkṛ",
    "prasāray",
    "kṣu",
    "nimi",
    "pratijñā",
    "atigāh",
    "anvavamṛś",
    "upaguh",
    "apabādh",
    "pṛtanāy",
    "upadru",
    "apigrah",
    "anuvyākhyā",
    "apipad",
    "ativṛdh",
    "nirvṛt",
    "anūdi",
    "āvraj",
    "pragrah",
    "śuśrūṣ",
    "tak",
    "ghuṣ",
    "apavṛ",
    "śośuc",
    "nind",
    "chanday",
    "chand",
    "bhuraṇy",
    "abhicākaś",
    "vyavacchid",
    "durasy",
    "an",
    "khid",
    "vyṛṣ",
    "uc",
    "arday",
    "acchāvad",
    "abhivah",
    "vivyadh",
    "sampariśri",
    "anūde",
    "vivṛh",
    "prajñāpay",
    "ākranday",
    "udañc",
    "nirjñā",
    "sampṛ",
    "paryāhṛ",
    "praskanday",
    "saṃvap",
    "abhyāgam",
    "upaghrā",
    "niḥsāray",
    "adhyavaso",
    "prasad",
    "udas",
    "sīv",
    "pratigṛ",
    "saṃgā",
    "parivad",
    "anvañj",
    "upaśī",
    "āccho",
    "apās",
    "upatṛd",
    "apamṛj",
    "pratyāvraj",
    "prajval",
    "nigṛ",
    "pratāpay",
    "pravartay",
    "prahas",
    "tuṣ",
    "prasnā",
    "prāvṛ",
    "abhighrā",
    "pariplu",
    "cetay",
    "samās",
    "vyāp",
    "viparyas",
    "vikṛṣ",
    "vigam",
    "ābhaj",
    "āpay",
    "prer",
    "paripaś",
    "vivad",
    "śnath",
    "anumad",
    "saṃhā",
    "er",
    "si",
    "mṛgay",
    "vici",
    "ākṛ",
    "pramud",
    "īṅkhay",
    "saṃyājay",
    "yātay",
    "sampāday",
    "ścut",
    "vimath",
    "upaśam",
    "ākāṅkṣ",
    "pratyānī",
    "vyutkram",
    "upāvanam",
    "avān",
    "parikṛṣ",
    "unnabhay",
    "atihā",
    "abhibhū",
    "avanij",
    "utsāday",
    "mūrchay",
    "saṃkṛṣ",
    "vidah",
    "sambhid",
    "saṃvah",
    "marcay",
    "upanāmay",
    "plāvay",
    "kāṅkṣ",
    "udāyu",
    "satkṛ",
    "kathay",
    "upāghrā",
    "anujñāpay",
    "vimṛś",
    "saṃśri",
    "upādā",
    "cintay",
    "anuṣañj",
    "paribādh",
    "vilāpay",
    "adhijāgṛ",
    "samanvārabh",
    "hāray",
    "prakṛṣ",
    "praticchad",
    "avaghrā",
    "nyas",
    "samārohay",
    "ucchid",
    "vyavasthā",
    "saṃhṛ",
    "māray",
    "pradih",
    "vyañj",
    "samprasru",
    "atiśī",
    "diś",
    "vijñāpay",
    "upalabh",
    "pratṛ",
    "lelāy",
    "anubhā",
    "abhyavahṛ",
    "haviṣkṛ",
    "śuṣ",
    "avabhṛ",
    "anusaṃsthā",
    "anuparī",
    "upavap",
    "āvay",
    "anuśaṃs",
    "tsar",
    "avacchid",
    "apyas",
    "mih",
    "anujan",
    "vinaś",
    "vinidhā",
    "āśaṃs",
    "apigam",
    "uparam",
    "nirvid",
    "apadru",
    "dhāvay",
    "anuprāṇ",
    "āj",
    "vṛṣāy",
    "raṃh",
    "ṛtāy",
    "dits",
    "brahmaṇy",
    "iyakṣ",
    "vicṛt",
    "gṛbhāy",
    "cekit",
    "yodhay",
    "viyu",
    "sridh",
    "dakṣ",
    "prakhyā",
    "chaday",
    "ribh",
    "vīḍay",
    "tuś",
    "tviṣ",
    "rap",
    "vip",
    "saṃpaś",
    "pruṣāy",
    "apacyu",
    "jaṅghan",
    "saṃśṛ",
    "do",
    "apinah",
    "āñj",
    "abhidhyai",
    "anunirvap",
    "apagā",
    "jijyūṣ",
    "apapravas",
    "utsic",
    "adhyas",
    "anvavadhā",
    "parāpū",
    "vivic",
    "abhisṛp",
    "parive",
    "paryālabh",
    "apidah",
    "avayaj",
    "upavājay",
    "paryañj",
    "pratiparī",
    "parākram",
    "tvar",
    "samāruh",
    "varṣay",
    "upavāsay",
    "abhipravah",
    "vikhid",
    "pratikhyā",
    "abhiduh",
    "nirvad"
  ]
}